{
    "cirq": {
        "cirq_followup": {
            "exception": null,
            "result": {
                "00110000000": 7,
                "00110000001": 6,
                "00110000010": 6,
                "00110000011": 6,
                "00110000100": 4,
                "00110000101": 6,
                "00110000110": 7,
                "00110000111": 2,
                "00110100000": 6,
                "00110100001": 7,
                "00110100010": 3,
                "00110100011": 5,
                "00110100100": 3,
                "00110100110": 9,
                "00110100111": 7,
                "00111000000": 247,
                "00111000001": 216,
                "00111000010": 236,
                "00111000011": 268,
                "00111000100": 263,
                "00111000101": 215,
                "00111000110": 228,
                "00111000111": 262,
                "00111100000": 240,
                "00111100001": 226,
                "00111100010": 267,
                "00111100011": 236,
                "00111100100": 240,
                "00111100101": 249,
                "00111100110": 241,
                "00111100111": 231,
                "10110000000": 3,
                "10110000001": 8,
                "10110000010": 4,
                "10110000011": 6,
                "10110000100": 5,
                "10110000101": 4,
                "10110000110": 3,
                "10110000111": 3,
                "10110100000": 4,
                "10110100001": 1,
                "10110100010": 5,
                "10110100100": 3,
                "10110100101": 7,
                "10110100110": 5,
                "10110100111": 5,
                "10111000000": 221,
                "10111000001": 232,
                "10111000010": 254,
                "10111000011": 261,
                "10111000100": 218,
                "10111000101": 250,
                "10111000110": 239,
                "10111000111": 219,
                "10111100000": 243,
                "10111100001": 249,
                "10111100010": 242,
                "10111100011": 240,
                "10111100100": 242,
                "10111100101": 235,
                "10111100110": 242,
                "10111100111": 236
            },
            "time_taken": "124.406625 ms"
        },
        "cirq_qasm_qiskit": {
            "exception": null,
            "result": {
                "00110000000": 8,
                "00110000011": 8,
                "00110000100": 5,
                "00110000101": 7,
                "00110000110": 4,
                "00110000111": 6,
                "00110100000": 4,
                "00110100001": 4,
                "00110100010": 3,
                "00110100011": 2,
                "00110100100": 6,
                "00110100101": 4,
                "00110100110": 3,
                "00110100111": 3,
                "00111000000": 237,
                "00111000001": 216,
                "00111000010": 233,
                "00111000011": 253,
                "00111000100": 244,
                "00111000101": 238,
                "00111000110": 239,
                "00111000111": 242,
                "00111100000": 253,
                "00111100001": 221,
                "00111100010": 229,
                "00111100011": 212,
                "00111100100": 259,
                "00111100101": 240,
                "00111100110": 257,
                "00111100111": 248,
                "10110000000": 9,
                "10110000001": 5,
                "10110000010": 3,
                "10110000011": 8,
                "10110000100": 4,
                "10110000101": 8,
                "10110000110": 3,
                "10110000111": 6,
                "10110100000": 4,
                "10110100001": 7,
                "10110100010": 3,
                "10110100011": 1,
                "10110100100": 5,
                "10110100101": 4,
                "10110100110": 4,
                "10110100111": 2,
                "10111000000": 227,
                "10111000001": 242,
                "10111000010": 252,
                "10111000011": 253,
                "10111000100": 256,
                "10111000101": 227,
                "10111000110": 246,
                "10111000111": 222,
                "10111100000": 245,
                "10111100001": 233,
                "10111100010": 216,
                "10111100011": 239,
                "10111100100": 230,
                "10111100101": 281,
                "10111100110": 264,
                "10111100111": 241
            },
            "time_taken": "4571.689125 ms"
        },
        "cirq_source": {
            "exception": null,
            "result": {
                "00110000000": 1,
                "00110000001": 1,
                "00110000010": 3,
                "00110000011": 8,
                "00110000100": 5,
                "00110000101": 8,
                "00110000110": 5,
                "00110000111": 3,
                "00110100000": 4,
                "00110100001": 5,
                "00110100010": 5,
                "00110100011": 8,
                "00110100100": 7,
                "00110100101": 4,
                "00110100110": 2,
                "00110100111": 5,
                "00111000000": 260,
                "00111000001": 231,
                "00111000010": 287,
                "00111000011": 242,
                "00111000100": 250,
                "00111000101": 208,
                "00111000110": 253,
                "00111000111": 233,
                "00111100000": 247,
                "00111100001": 236,
                "00111100010": 238,
                "00111100011": 253,
                "00111100100": 256,
                "00111100101": 241,
                "00111100110": 237,
                "00111100111": 226,
                "10110000000": 4,
                "10110000001": 3,
                "10110000010": 4,
                "10110000011": 5,
                "10110000100": 7,
                "10110000101": 4,
                "10110000110": 6,
                "10110000111": 3,
                "10110100000": 2,
                "10110100001": 8,
                "10110100010": 4,
                "10110100011": 6,
                "10110100100": 3,
                "10110100101": 5,
                "10110100110": 6,
                "10110100111": 4,
                "10111000000": 261,
                "10111000001": 246,
                "10111000010": 288,
                "10111000011": 222,
                "10111000100": 242,
                "10111000101": 247,
                "10111000110": 235,
                "10111000111": 255,
                "10111100000": 242,
                "10111100001": 218,
                "10111100010": 208,
                "10111100011": 223,
                "10111100100": 201,
                "10111100101": 238,
                "10111100110": 221,
                "10111100111": 245
            },
            "time_taken": "88.916917 ms"
        },
        "config": {
            "cirq_qasm_qiskit": true,
            "qubit_order": {
                "0": 2,
                "1": 5,
                "2": 1,
                "3": 10,
                "4": 8,
                "5": 0,
                "6": 6,
                "7": 4,
                "8": 3,
                "9": 7,
                "10": 9
            },
            "relations": [
                "ToQasmAndBack",
                "ChangeQubitOrder"
            ]
        },
        "followup_cirq_qasm_qiskit_divergence": {
            "p-value": 0.49520620648384833,
            "statistic": 0.013268690992600153
        },
        "source_cirq_qasm_qiskit_divergence": {
            "p-value": 0.08965168218099646,
            "statistic": 0.01990303648890023
        },
        "source_followup_divergence": {
            "p-value": 0.20913207353339,
            "statistic": 0.016968614442459812
        }
    },
    "prog_id": "b03a1110b4144365881d8a00aa9fb594",
    "pyquil": {
        "config": {
            "qasm_roundtrip": true,
            "qubit_order": {
                "0": 2,
                "1": 5,
                "2": 1,
                "3": 10,
                "4": 8,
                "5": 0,
                "6": 6,
                "7": 4,
                "8": 3,
                "9": 7,
                "10": 9
            },
            "relations": [
                "ToQasmAndBack",
                "ChangeQubitOrder"
            ]
        },
        "pyquil_followup": {
            "exception": null,
            "result": {
                "00110000000": 8,
                "00110000001": 6,
                "00110000010": 4,
                "00110000011": 5,
                "00110000100": 4,
                "00110000101": 5,
                "00110000110": 1,
                "00110000111": 8,
                "00110100000": 2,
                "00110100001": 5,
                "00110100010": 4,
                "00110100011": 8,
                "00110100100": 9,
                "00110100101": 3,
                "00110100110": 4,
                "00110100111": 6,
                "00111000000": 251,
                "00111000001": 239,
                "00111000010": 233,
                "00111000011": 247,
                "00111000100": 243,
                "00111000101": 236,
                "00111000110": 237,
                "00111000111": 255,
                "00111100000": 243,
                "00111100001": 238,
                "00111100010": 235,
                "00111100011": 252,
                "00111100100": 245,
                "00111100101": 246,
                "00111100110": 248,
                "00111100111": 271,
                "10110000000": 10,
                "10110000001": 6,
                "10110000010": 2,
                "10110000011": 5,
                "10110000100": 7,
                "10110000101": 6,
                "10110000110": 6,
                "10110000111": 5,
                "10110100000": 3,
                "10110100001": 3,
                "10110100010": 6,
                "10110100011": 5,
                "10110100100": 1,
                "10110100101": 3,
                "10110100110": 2,
                "10110100111": 6,
                "10111000000": 244,
                "10111000001": 226,
                "10111000010": 243,
                "10111000011": 208,
                "10111000100": 229,
                "10111000101": 224,
                "10111000110": 260,
                "10111000111": 278,
                "10111100000": 217,
                "10111100001": 235,
                "10111100010": 243,
                "10111100011": 225,
                "10111100100": 231,
                "10111100101": 228,
                "10111100110": 237,
                "10111100111": 233
            },
            "time_taken": "2797.718584 ms"
        },
        "pyquil_source": {
            "exception": null,
            "result": {
                "00110000000": 4,
                "00110000001": 4,
                "00110000010": 5,
                "00110000011": 4,
                "00110000100": 1,
                "00110000101": 5,
                "00110000110": 3,
                "00110000111": 5,
                "00110100000": 3,
                "00110100001": 4,
                "00110100010": 4,
                "00110100011": 4,
                "00110100100": 7,
                "00110100101": 1,
                "00110100110": 2,
                "00110100111": 10,
                "00111000000": 258,
                "00111000001": 270,
                "00111000010": 246,
                "00111000011": 233,
                "00111000100": 273,
                "00111000101": 235,
                "00111000110": 258,
                "00111000111": 220,
                "00111100000": 256,
                "00111100001": 221,
                "00111100010": 238,
                "00111100011": 235,
                "00111100100": 231,
                "00111100101": 253,
                "00111100110": 222,
                "00111100111": 257,
                "10110000000": 5,
                "10110000001": 3,
                "10110000010": 5,
                "10110000011": 4,
                "10110000100": 5,
                "10110000101": 5,
                "10110000110": 5,
                "10110000111": 5,
                "10110100000": 1,
                "10110100001": 9,
                "10110100010": 1,
                "10110100011": 6,
                "10110100100": 3,
                "10110100101": 5,
                "10110100110": 2,
                "10110100111": 4,
                "10111000000": 234,
                "10111000001": 210,
                "10111000010": 250,
                "10111000011": 229,
                "10111000100": 246,
                "10111000101": 205,
                "10111000110": 254,
                "10111000111": 248,
                "10111100000": 244,
                "10111100001": 225,
                "10111100010": 263,
                "10111100011": 232,
                "10111100100": 238,
                "10111100101": 249,
                "10111100110": 217,
                "10111100111": 254
            },
            "time_taken": "2692.916208 ms"
        },
        "source_followup_divergence": {
            "p-value": 0.8859302250981547,
            "statistic": 0.009313600408267415
        }
    },
    "qiskit": {
        "qasm3_followup_divergence": null,
        "qasm3_roundtrip": {
            "exception": "61,15: type error",
            "result": null,
            "time_taken": null
        },
        "qasm3_source_divergence": null,
        "qiskit_followup": {
            "exception": null,
            "result": {
                "00110000000": 7,
                "00110000001": 4,
                "00110000010": 8,
                "00110000011": 3,
                "00110000100": 5,
                "00110000101": 7,
                "00110000110": 8,
                "00110000111": 9,
                "00110100000": 2,
                "00110100001": 7,
                "00110100010": 3,
                "00110100011": 7,
                "00110100100": 7,
                "00110100101": 6,
                "00110100110": 6,
                "00110100111": 3,
                "00111000000": 235,
                "00111000001": 252,
                "00111000010": 224,
                "00111000011": 238,
                "00111000100": 227,
                "00111000101": 250,
                "00111000110": 268,
                "00111000111": 229,
                "00111100000": 222,
                "00111100001": 273,
                "00111100010": 256,
                "00111100011": 258,
                "00111100100": 245,
                "00111100101": 230,
                "00111100110": 217,
                "00111100111": 220,
                "10110000000": 4,
                "10110000001": 3,
                "10110000010": 8,
                "10110000011": 4,
                "10110000100": 5,
                "10110000101": 2,
                "10110000110": 5,
                "10110000111": 2,
                "10110100000": 2,
                "10110100001": 4,
                "10110100010": 3,
                "10110100011": 8,
                "10110100100": 5,
                "10110100101": 3,
                "10110100110": 5,
                "10110100111": 6,
                "10111000000": 235,
                "10111000001": 246,
                "10111000010": 222,
                "10111000011": 236,
                "10111000100": 225,
                "10111000101": 249,
                "10111000110": 251,
                "10111000111": 241,
                "10111100000": 269,
                "10111100001": 230,
                "10111100010": 242,
                "10111100011": 254,
                "10111100100": 217,
                "10111100101": 232,
                "10111100110": 251,
                "10111100111": 233
            },
            "result_original": {
                "00000011000": 7,
                "00000011001": 2,
                "00000011010": 5,
                "00000011011": 7,
                "00000011100": 4,
                "00000011101": 7,
                "00000011110": 7,
                "00000011111": 6,
                "00000111000": 8,
                "00000111001": 3,
                "00000111010": 8,
                "00000111011": 6,
                "00000111100": 3,
                "00000111101": 7,
                "00000111110": 9,
                "00000111111": 3,
                "00001011000": 235,
                "00001011001": 222,
                "00001011010": 227,
                "00001011011": 245,
                "00001011100": 252,
                "00001011101": 273,
                "00001011110": 250,
                "00001011111": 230,
                "00001111000": 224,
                "00001111001": 256,
                "00001111010": 268,
                "00001111011": 217,
                "00001111100": 238,
                "00001111101": 258,
                "00001111110": 229,
                "00001111111": 220,
                "01000011000": 4,
                "01000011001": 2,
                "01000011010": 5,
                "01000011011": 5,
                "01000011100": 3,
                "01000011101": 4,
                "01000011110": 2,
                "01000011111": 3,
                "01000111000": 8,
                "01000111001": 3,
                "01000111010": 5,
                "01000111011": 5,
                "01000111100": 4,
                "01000111101": 8,
                "01000111110": 2,
                "01000111111": 6,
                "01001011000": 235,
                "01001011001": 269,
                "01001011010": 225,
                "01001011011": 217,
                "01001011100": 246,
                "01001011101": 230,
                "01001011110": 249,
                "01001011111": 232,
                "01001111000": 222,
                "01001111001": 242,
                "01001111010": 251,
                "01001111011": 251,
                "01001111100": 236,
                "01001111101": 254,
                "01001111110": 241,
                "01001111111": 233
            },
            "time_taken": "69.400042 ms"
        },
        "qiskit_source": {
            "exception": null,
            "result": {
                "00110000000": 4,
                "00110000001": 5,
                "00110000010": 2,
                "00110000011": 6,
                "00110000100": 5,
                "00110000101": 11,
                "00110000110": 3,
                "00110000111": 6,
                "00110100000": 5,
                "00110100001": 1,
                "00110100010": 3,
                "00110100011": 3,
                "00110100100": 2,
                "00110100101": 6,
                "00110100110": 6,
                "00110100111": 5,
                "00111000000": 250,
                "00111000001": 228,
                "00111000010": 253,
                "00111000011": 224,
                "00111000100": 253,
                "00111000101": 224,
                "00111000110": 260,
                "00111000111": 216,
                "00111100000": 245,
                "00111100001": 246,
                "00111100010": 262,
                "00111100011": 237,
                "00111100100": 258,
                "00111100101": 243,
                "00111100110": 221,
                "00111100111": 231,
                "10110000000": 3,
                "10110000001": 3,
                "10110000010": 5,
                "10110000011": 5,
                "10110000100": 3,
                "10110000101": 4,
                "10110000110": 6,
                "10110000111": 6,
                "10110100000": 5,
                "10110100001": 4,
                "10110100010": 4,
                "10110100011": 2,
                "10110100100": 9,
                "10110100101": 7,
                "10110100110": 4,
                "10110100111": 6,
                "10111000000": 237,
                "10111000001": 259,
                "10111000010": 258,
                "10111000011": 238,
                "10111000100": 240,
                "10111000101": 233,
                "10111000110": 231,
                "10111000111": 256,
                "10111100000": 251,
                "10111100001": 249,
                "10111100010": 213,
                "10111100011": 222,
                "10111100100": 222,
                "10111100101": 232,
                "10111100110": 241,
                "10111100111": 256
            },
            "time_taken": "47.733708 ms"
        },
        "qpy_followup_divergence": {
            "p-value": 0.6662900399325051,
            "statistic": 0.011610104618525133
        },
        "qpy_roundtrip": {
            "exception": null,
            "result": {
                "00110000000": 8,
                "00110000001": 7,
                "00110000010": 2,
                "00110000011": 5,
                "00110000100": 4,
                "00110000101": 1,
                "00110000110": 3,
                "00110000111": 3,
                "00110100000": 7,
                "00110100001": 3,
                "00110100010": 1,
                "00110100011": 6,
                "00110100100": 5,
                "00110100101": 6,
                "00110100110": 3,
                "00110100111": 4,
                "00111000000": 212,
                "00111000001": 260,
                "00111000010": 236,
                "00111000011": 252,
                "00111000100": 242,
                "00111000101": 238,
                "00111000110": 234,
                "00111000111": 247,
                "00111100000": 220,
                "00111100001": 262,
                "00111100010": 253,
                "00111100011": 266,
                "00111100100": 232,
                "00111100101": 243,
                "00111100110": 254,
                "00111100111": 274,
                "10110000000": 4,
                "10110000001": 5,
                "10110000010": 6,
                "10110000011": 4,
                "10110000100": 5,
                "10110000101": 2,
                "10110000110": 11,
                "10110000111": 5,
                "10110100000": 6,
                "10110100001": 5,
                "10110100010": 6,
                "10110100011": 2,
                "10110100100": 5,
                "10110100101": 3,
                "10110100110": 3,
                "10110100111": 2,
                "10111000000": 245,
                "10111000001": 219,
                "10111000010": 253,
                "10111000011": 251,
                "10111000100": 221,
                "10111000101": 207,
                "10111000110": 242,
                "10111000111": 266,
                "10111100000": 208,
                "10111100001": 216,
                "10111100010": 244,
                "10111100011": 264,
                "10111100100": 229,
                "10111100101": 245,
                "10111100110": 219,
                "10111100111": 242
            },
            "result_original": {
                "00000011000": 8,
                "00000011001": 7,
                "00000011010": 4,
                "00000011011": 5,
                "00000011100": 7,
                "00000011101": 3,
                "00000011110": 1,
                "00000011111": 6,
                "00000111000": 2,
                "00000111001": 1,
                "00000111010": 3,
                "00000111011": 3,
                "00000111100": 5,
                "00000111101": 6,
                "00000111110": 3,
                "00000111111": 4,
                "00001011000": 212,
                "00001011001": 220,
                "00001011010": 242,
                "00001011011": 232,
                "00001011100": 260,
                "00001011101": 262,
                "00001011110": 238,
                "00001011111": 243,
                "00001111000": 236,
                "00001111001": 253,
                "00001111010": 234,
                "00001111011": 254,
                "00001111100": 252,
                "00001111101": 266,
                "00001111110": 247,
                "00001111111": 274,
                "01000011000": 4,
                "01000011001": 6,
                "01000011010": 5,
                "01000011011": 5,
                "01000011100": 5,
                "01000011101": 5,
                "01000011110": 2,
                "01000011111": 3,
                "01000111000": 6,
                "01000111001": 6,
                "01000111010": 11,
                "01000111011": 3,
                "01000111100": 4,
                "01000111101": 2,
                "01000111110": 5,
                "01000111111": 2,
                "01001011000": 245,
                "01001011001": 208,
                "01001011010": 221,
                "01001011011": 229,
                "01001011100": 219,
                "01001011101": 216,
                "01001011110": 207,
                "01001011111": 245,
                "01001111000": 253,
                "01001111001": 244,
                "01001111010": 242,
                "01001111011": 219,
                "01001111100": 251,
                "01001111101": 264,
                "01001111110": 266,
                "01001111111": 242
            },
            "time_taken": "48.681959 ms"
        },
        "qpy_source_divergence": {
            "p-value": 0.8089305959517064,
            "statistic": 0.010206685378923195
        },
        "source_followup_divergence": {
            "p-value": 0.9618937698753659,
            "statistic": 0.008037764735902016
        }
    },
    "unitary": {
        "cirq_unitary": {
            "exception": null,
            "result": {
                "00110000000": 2,
                "00110000001": 4,
                "00110000010": 4,
                "00110000011": 9,
                "00110000100": 3,
                "00110000101": 5,
                "00110000110": 6,
                "00110000111": 8,
                "00110100000": 8,
                "00110100001": 7,
                "00110100010": 4,
                "00110100011": 5,
                "00110100100": 3,
                "00110100101": 5,
                "00110100110": 7,
                "00110100111": 6,
                "00111000000": 241,
                "00111000001": 251,
                "00111000010": 253,
                "00111000011": 234,
                "00111000100": 248,
                "00111000101": 263,
                "00111000110": 230,
                "00111000111": 249,
                "00111100000": 265,
                "00111100001": 247,
                "00111100010": 241,
                "00111100011": 233,
                "00111100100": 248,
                "00111100101": 254,
                "00111100110": 277,
                "00111100111": 227,
                "10110000000": 2,
                "10110000001": 3,
                "10110000010": 7,
                "10110000011": 5,
                "10110000100": 7,
                "10110000101": 2,
                "10110000110": 4,
                "10110000111": 6,
                "10110100000": 8,
                "10110100001": 6,
                "10110100010": 4,
                "10110100011": 6,
                "10110100100": 3,
                "10110100101": 3,
                "10110100110": 6,
                "10110100111": 2,
                "10111000000": 246,
                "10111000001": 218,
                "10111000010": 244,
                "10111000011": 231,
                "10111000100": 246,
                "10111000101": 213,
                "10111000110": 235,
                "10111000111": 241,
                "10111100000": 214,
                "10111100001": 232,
                "10111100010": 217,
                "10111100011": 219,
                "10111100100": 224,
                "10111100101": 241,
                "10111100110": 248,
                "10111100111": 248
            },
            "time_taken": "962.162792 ms"
        },
        "pyquil_unitary": {
            "exception": "RCCX",
            "result": null,
            "time_taken": null
        },
        "qiskit_unitary": {
            "exception": null,
            "result": {
                "00000011000": 3,
                "00000011001": 7,
                "00000011010": 5,
                "00000011011": 5,
                "00000011100": 6,
                "00000011101": 10,
                "00000011110": 9,
                "00000011111": 4,
                "00000111000": 1,
                "00000111001": 5,
                "00000111010": 3,
                "00000111011": 2,
                "00000111100": 3,
                "00000111101": 3,
                "00000111110": 3,
                "00000111111": 11,
                "00001011000": 233,
                "00001011001": 225,
                "00001011010": 229,
                "00001011011": 250,
                "00001011100": 247,
                "00001011101": 198,
                "00001011110": 221,
                "00001011111": 254,
                "00001111000": 228,
                "00001111001": 246,
                "00001111010": 234,
                "00001111011": 254,
                "00001111100": 232,
                "00001111101": 227,
                "00001111110": 262,
                "00001111111": 248,
                "01000011000": 4,
                "01000011001": 2,
                "01000011010": 4,
                "01000011011": 5,
                "01000011100": 6,
                "01000011101": 3,
                "01000011110": 4,
                "01000011111": 5,
                "01000111000": 7,
                "01000111001": 5,
                "01000111010": 5,
                "01000111011": 8,
                "01000111100": 4,
                "01000111101": 3,
                "01000111110": 6,
                "01000111111": 7,
                "01001011000": 264,
                "01001011001": 240,
                "01001011010": 219,
                "01001011011": 205,
                "01001011100": 265,
                "01001011101": 227,
                "01001011110": 258,
                "01001011111": 249,
                "01001111000": 229,
                "01001111001": 271,
                "01001111010": 237,
                "01001111011": 220,
                "01001111100": 265,
                "01001111101": 248,
                "01001111110": 240,
                "01001111111": 255
            },
            "time_taken": "191.719083 ms"
        },
        "unitary": false
    }
}