{
    "cirq": {
        "cirq_followup": {
            "exception": "Simulator doesn't support <bloqs.ext.cirq.gates.U2Gate object at 0x1740649d0>.on(cirq.NamedQubit('q2'))",
            "result": null,
            "time_taken": null
        },
        "cirq_source": {
            "exception": null,
            "result": {
                "00010000000": 937,
                "00010000100": 979,
                "00010100000": 977,
                "00010100100": 981,
                "10010000000": 960,
                "10010000100": 1016,
                "10010100000": 1010,
                "10010100100": 978
            },
            "time_taken": "89.903875 ms"
        },
        "config": {
            "inject_params": {
                "p_3efaaf": 2.5163050709890156,
                "p_637ac4": 2.1276323672732023,
                "p_670928": 4.028174522740928,
                "p_779c94": 4.2641612072511235,
                "p_9e6f86": 3.950837470808744,
                "p_c2a67e": 4.722103101046168,
                "p_d78b4f": 4.229610589867865
            },
            "relations": [
                "InjectParameters"
            ]
        },
        "source_followup_divergence": null
    },
    "prog_id": "a7914c0146db4b45ad08414b8d39669c",
    "pyquil": {
        "config": {
            "inject_params": {
                "p_3efaaf": 2.5163050709890156,
                "p_637ac4": 2.1276323672732023,
                "p_670928": 4.028174522740928,
                "p_779c94": 4.2641612072511235,
                "p_9e6f86": 3.950837470808744,
                "p_c2a67e": 4.722103101046168,
                "p_d78b4f": 4.229610589867865
            },
            "relations": [
                "InjectParameters"
            ]
        },
        "pyquil_followup": {
            "exception": "Unhandled error in host program:\nCondition CL-QUIL::COMPILER-DOES-NOT-APPLY was signalled.",
            "result": null,
            "time_taken": null
        },
        "pyquil_source": {
            "exception": null,
            "result": {
                "00010000000": 944,
                "00010000100": 1000,
                "00010100000": 937,
                "00010100100": 1016,
                "10010000000": 960,
                "10010000100": 965,
                "10010100000": 976,
                "10010100100": 1040
            },
            "time_taken": "3956.665417 ms"
        },
        "source_followup_divergence": null
    },
    "qiskit": {
        "qiskit_followup": {
            "exception": null,
            "result": {
                "00010000000": 987,
                "00010000100": 928,
                "00010100000": 1023,
                "00010100100": 964,
                "10010000000": 991,
                "10010000100": 1014,
                "10010100000": 949,
                "10010100100": 982
            },
            "time_taken": "41.878917 ms"
        },
        "qiskit_source": {
            "exception": null,
            "result": {
                "00010000000": 974,
                "00010000100": 977,
                "00010100000": 1010,
                "00010100100": 955,
                "10010000000": 919,
                "10010000100": 975,
                "10010100000": 1027,
                "10010100100": 1001
            },
            "time_taken": "46.133541 ms"
        },
        "source_followup_divergence": {
            "p-value": 0.5857674559437759,
            "statistic": 0.012375606021944374
        }
    }
}