{
    "cirq": {
        "cirq_followup": {
            "exception": null,
            "result": {
                "00000010": 33,
                "00000011": 10,
                "00000110": 94,
                "00000111": 39,
                "00001111": 10,
                "00010010": 139,
                "00010011": 121,
                "00010110": 22,
                "00010111": 48,
                "00011011": 8,
                "00011111": 4,
                "00111011": 7,
                "01000010": 29,
                "01000011": 4,
                "01000110": 104,
                "01000111": 112,
                "01001011": 1,
                "01001111": 6,
                "01010010": 208,
                "01010011": 232,
                "01010110": 85,
                "01010111": 16,
                "01011011": 33,
                "01101011": 1,
                "01101111": 6,
                "01111111": 1,
                "10000010": 32,
                "10000011": 15,
                "10000110": 91,
                "10000111": 51,
                "10001111": 17,
                "10010010": 144,
                "10010011": 143,
                "10010110": 20,
                "10010111": 47,
                "10011011": 3,
                "10011111": 8,
                "10101011": 2,
                "10111011": 9,
                "11000010": 60,
                "11000011": 5,
                "11000110": 76,
                "11000111": 100,
                "11001011": 1,
                "11001111": 2,
                "11010010": 210,
                "11010011": 218,
                "11010110": 94,
                "11010111": 18,
                "11011011": 21,
                "11101011": 1,
                "11101111": 8,
                "11111111": 2
            },
            "time_taken": "27.932042 ms"
        },
        "cirq_source": {
            "exception": null,
            "result": {
                "00000010": 32,
                "00000011": 12,
                "00000110": 93,
                "00000111": 54,
                "00001011": 1,
                "00001111": 18,
                "00010010": 140,
                "00010011": 131,
                "00010110": 28,
                "00010111": 48,
                "00011011": 10,
                "00011111": 8,
                "00101011": 1,
                "00111011": 9,
                "01000010": 55,
                "01000011": 8,
                "01000110": 73,
                "01000111": 108,
                "01001111": 4,
                "01010010": 188,
                "01010011": 196,
                "01010110": 81,
                "01010111": 12,
                "01011011": 38,
                "01101111": 8,
                "10000010": 43,
                "10000011": 6,
                "10000110": 94,
                "10000111": 44,
                "10001011": 1,
                "10001111": 9,
                "10010010": 145,
                "10010011": 152,
                "10010110": 23,
                "10010111": 43,
                "10011011": 8,
                "10011111": 7,
                "10101011": 1,
                "10111011": 10,
                "11000010": 39,
                "11000011": 2,
                "11000110": 91,
                "11000111": 106,
                "11001011": 1,
                "11001111": 6,
                "11010010": 187,
                "11010011": 252,
                "11010110": 97,
                "11010111": 14,
                "11011011": 25,
                "11101111": 7,
                "11111111": 2
            },
            "time_taken": "27.866417 ms"
        },
        "config": {
            "qubit_order": {
                "0": 1,
                "1": 6,
                "2": 3,
                "3": 2,
                "4": 0,
                "5": 7,
                "6": 5,
                "7": 4
            },
            "relations": [
                "ChangeQubitOrder"
            ]
        },
        "source_followup_divergence": {
            "p-value": 0.19842016285569308,
            "statistic": 0.028870443883074703
        }
    },
    "prog_id": "7a0852b0228e49d5a264d07cb38e28e7",
    "pyquil": {
        "config": {
            "qubit_order": {
                "0": 1,
                "1": 6,
                "2": 3,
                "3": 2,
                "4": 0,
                "5": 7,
                "6": 5,
                "7": 4
            },
            "relations": [
                "ChangeQubitOrder"
            ]
        },
        "pyquil_followup": {
            "exception": "Timeout on client tcp://127.0.0.1:5555, method name quil_to_native_quil, class info: <rpcq._client.Client object at 0x16a5da6a0>",
            "result": null,
            "time_taken": null
        },
        "pyquil_source": {
            "exception": null,
            "result": {
                "00000010": 43,
                "00000011": 13,
                "00000110": 84,
                "00000111": 44,
                "00001011": 1,
                "00001111": 12,
                "00010010": 134,
                "00010011": 118,
                "00010110": 18,
                "00010111": 55,
                "00011011": 4,
                "00011111": 5,
                "00111011": 15,
                "01000010": 39,
                "01000011": 3,
                "01000110": 82,
                "01000111": 107,
                "01001011": 2,
                "01001111": 7,
                "01010010": 213,
                "01010011": 263,
                "01010110": 81,
                "01010111": 21,
                "01011011": 40,
                "01011111": 1,
                "01101111": 6,
                "01111011": 1,
                "01111111": 1,
                "10000010": 28,
                "10000011": 6,
                "10000110": 93,
                "10000111": 51,
                "10001111": 12,
                "10010010": 136,
                "10010011": 129,
                "10010110": 19,
                "10010111": 51,
                "10011011": 8,
                "10011111": 13,
                "10101011": 3,
                "10111011": 7,
                "11000010": 34,
                "11000011": 9,
                "11000110": 87,
                "11000111": 87,
                "11001011": 1,
                "11001111": 7,
                "11010010": 206,
                "11010011": 212,
                "11010110": 94,
                "11010111": 17,
                "11011011": 38,
                "11101011": 1,
                "11101111": 7,
                "11111011": 1,
                "11111111": 1
            },
            "time_taken": "24724.186 ms"
        },
        "source_followup_divergence": null
    },
    "qiskit": {
        "qiskit_followup": {
            "exception": null,
            "result": {
                "00000010": 38,
                "00000011": 4,
                "00000110": 93,
                "00000111": 44,
                "00001011": 1,
                "00001111": 11,
                "00010010": 136,
                "00010011": 134,
                "00010110": 33,
                "00010111": 54,
                "00011011": 4,
                "00011111": 8,
                "00101011": 1,
                "00111011": 12,
                "00111111": 1,
                "01000010": 34,
                "01000011": 4,
                "01000110": 78,
                "01000111": 108,
                "01001011": 3,
                "01001111": 6,
                "01010010": 198,
                "01010011": 219,
                "01010110": 86,
                "01010111": 11,
                "01011011": 25,
                "01101111": 5,
                "01111111": 2,
                "10000010": 38,
                "10000011": 14,
                "10000110": 81,
                "10000111": 52,
                "10001111": 13,
                "10010010": 112,
                "10010011": 186,
                "10010110": 24,
                "10010111": 49,
                "10011011": 9,
                "10011111": 6,
                "10111011": 10,
                "11000010": 42,
                "11000011": 2,
                "11000110": 90,
                "11000111": 111,
                "11001011": 1,
                "11001111": 7,
                "11010010": 187,
                "11010011": 241,
                "11010110": 84,
                "11010111": 14,
                "11011011": 34,
                "11101111": 8,
                "11111111": 3
            },
            "result_original": {
                "01000000": 38,
                "01000001": 136,
                "01000010": 4,
                "01000011": 134,
                "01000110": 1,
                "01000111": 4,
                "01001000": 93,
                "01001001": 33,
                "01001010": 44,
                "01001011": 54,
                "01001110": 11,
                "01001111": 8,
                "01010000": 38,
                "01010001": 112,
                "01010010": 14,
                "01010011": 186,
                "01010111": 9,
                "01011000": 81,
                "01011001": 24,
                "01011010": 52,
                "01011011": 49,
                "01011110": 13,
                "01011111": 6,
                "01100000": 34,
                "01100001": 198,
                "01100010": 4,
                "01100011": 219,
                "01100110": 3,
                "01100111": 25,
                "01101000": 78,
                "01101001": 86,
                "01101010": 108,
                "01101011": 11,
                "01101110": 6,
                "01110000": 42,
                "01110001": 187,
                "01110010": 2,
                "01110011": 241,
                "01110110": 1,
                "01110111": 34,
                "01111000": 90,
                "01111001": 84,
                "01111010": 111,
                "01111011": 14,
                "01111110": 7,
                "11000110": 1,
                "11000111": 12,
                "11001111": 1,
                "11010111": 10,
                "11101110": 5,
                "11101111": 2,
                "11111110": 8,
                "11111111": 3
            },
            "time_taken": "115.503458 ms"
        },
        "qiskit_source": {
            "exception": null,
            "result": {
                "00000010": 29,
                "00000011": 15,
                "00000110": 86,
                "00000111": 56,
                "00001011": 1,
                "00001111": 6,
                "00010010": 135,
                "00010011": 127,
                "00010110": 23,
                "00010111": 46,
                "00011011": 6,
                "00011111": 10,
                "00101011": 1,
                "00111011": 7,
                "00111111": 1,
                "01000010": 41,
                "01000011": 1,
                "01000110": 92,
                "01000111": 106,
                "01001011": 2,
                "01001111": 5,
                "01010010": 213,
                "01010011": 213,
                "01010110": 92,
                "01010111": 14,
                "01011011": 36,
                "01101011": 1,
                "01101111": 7,
                "01111111": 2,
                "10000010": 33,
                "10000011": 11,
                "10000110": 92,
                "10000111": 48,
                "10001111": 10,
                "10010010": 138,
                "10010011": 143,
                "10010110": 31,
                "10010111": 57,
                "10011011": 13,
                "10011111": 9,
                "10101011": 2,
                "10111011": 6,
                "10111111": 1,
                "11000010": 41,
                "11000011": 4,
                "11000110": 85,
                "11000111": 113,
                "11001011": 1,
                "11001111": 8,
                "11010010": 175,
                "11010011": 236,
                "11010110": 92,
                "11010111": 19,
                "11011011": 26,
                "11101111": 3
            },
            "time_taken": "116.158167 ms"
        },
        "source_followup_divergence": {
            "p-value": 0.8925521148918594,
            "statistic": 0.015517863587152653
        }
    }
}