{
    "cirq": {
        "cirq_followup": {
            "exception": null,
            "result": {
                "01000": 979
            },
            "time_taken": "21.604292 ms"
        },
        "cirq_qasm_qiskit": {
            "exception": null,
            "result": {
                "01000": 979
            },
            "time_taken": "48.022292 ms"
        },
        "cirq_source": {
            "exception": null,
            "result": {
                "01000": 979
            },
            "time_taken": "7.721167 ms"
        },
        "config": {
            "cirq_qasm_qiskit": true,
            "inject_params": {
                "p_3c4bb1": 6.163759533339787,
                "p_5e74b9": 2.0099472182748075
            },
            "relations": [
                "ToQasmAndBack",
                "ChangeCouplingMap",
                "InjectParameters",
                "ChangeCouplingMap"
            ]
        },
        "followup_cirq_qasm_qiskit_divergence": {
            "p-value": 1.0,
            "statistic": 0.0
        },
        "source_cirq_qasm_qiskit_divergence": {
            "p-value": 1.0,
            "statistic": 0.0
        },
        "source_followup_divergence": {
            "p-value": 1.0,
            "statistic": 0.0
        }
    },
    "prog_id": "fd49fc92775a417388be4fa925b354bf",
    "pyquil": {
        "config": {
            "inject_params": {
                "p_3c4bb1": 6.163759533339787,
                "p_5e74b9": 2.0099472182748075
            },
            "qasm_roundtrip": true,
            "relations": [
                "ToQasmAndBack",
                "ChangeCouplingMap",
                "InjectParameters",
                "ChangeCouplingMap"
            ]
        },
        "pyquil_followup": {
            "exception": "Unhandled error in host program:\nCondition CL-QUIL::COMPILER-DOES-NOT-APPLY was signalled.",
            "result": null,
            "time_taken": null
        },
        "pyquil_source": {
            "exception": null,
            "result": {
                "01000": 979
            },
            "time_taken": "353.553208 ms"
        },
        "source_followup_divergence": null
    },
    "qiskit": {
        "qasm3_followup_divergence": null,
        "qasm3_roundtrip": {
            "exception": null,
            "result": {
                "01000": 979
            },
            "time_taken": "22.708834 ms"
        },
        "qasm3_source_divergence": {
            "p-value": 1.0,
            "statistic": 0.0
        },
        "qiskit_followup": {
            "exception": "Duplicate declaration for gate 'rzx' at line 4, file .\\nPrevious occurrence at line 3, file ",
            "result": null,
            "time_taken": null
        },
        "qiskit_source": {
            "exception": null,
            "result": {
                "01000": 979
            },
            "time_taken": "8.380375 ms"
        },
        "qpy_followup_divergence": null,
        "qpy_roundtrip": {
            "exception": null,
            "result": {
                "01000": 979
            },
            "time_taken": "19.950208 ms"
        },
        "qpy_source_divergence": {
            "p-value": 1.0,
            "statistic": 0.0
        },
        "source_followup_divergence": null
    }
}